LICENSE
MANIFEST.in
README.rst
gpl-2.0.txt
setup.py
scripts/genkrb5conf
scripts/typeperf
scripts/wecutil
scripts/winrm
scripts/winrs
txwinrm/__init__.py
txwinrm/app.py
txwinrm/collect.py
txwinrm/constants.py
txwinrm/enumerate.py
txwinrm/genkrb5conf.py
txwinrm/shell.py
txwinrm/subscribe.py
txwinrm/typeperf.py
txwinrm/util.py
txwinrm/wecutil.py
txwinrm/winrm.py
txwinrm/winrs.py
txwinrm.egg-info/PKG-INFO
txwinrm.egg-info/SOURCES.txt
txwinrm.egg-info/dependency_links.txt
txwinrm.egg-info/requires.txt
txwinrm.egg-info/test_info.txt
txwinrm.egg-info/top_level.txt
txwinrm/request/__init__.py
txwinrm/request/command.xml
txwinrm/request/create.xml
txwinrm/request/delete.xml
txwinrm/request/enumerate.xml
txwinrm/request/event_pull.xml
txwinrm/request/pull.xml
txwinrm/request/receive.xml
txwinrm/request/send.xml
txwinrm/request/signal.xml
txwinrm/request/subscribe.xml
txwinrm/request/unsubscribe.xml