Metadata-Version: 1.0
Name: txwinrm
Version: 0.9.5
Summary: Asynchronous Python WinRM client
Home-page: https://github.com/zenoss/txwinrm
Author: Zenoss
Author-email: bedwards@zenoss.com
License: See LICENSE file
Platform: UNKNOWN
